sahara_dashboard/__init__.py
sahara_dashboard/exceptions.py
sahara_dashboard/utils.py
sahara_dashboard/version.py
sahara_dashboard/api/__init__.py
sahara_dashboard/api/designate.py
sahara_dashboard/api/manila.py
sahara_dashboard/api/sahara.py
sahara_dashboard/content/__init__.py
sahara_dashboard/content/data_processing/__init__.py
sahara_dashboard/content/data_processing/tables.py
sahara_dashboard/content/data_processing/tabs.py
sahara_dashboard/content/data_processing/clusters/__init__.py
sahara_dashboard/content/data_processing/clusters/panel.py
sahara_dashboard/content/data_processing/clusters/urls.py
sahara_dashboard/content/data_processing/clusters/views.py
sahara_dashboard/content/data_processing/clusters/cluster_templates/__init__.py
sahara_dashboard/content/data_processing/clusters/cluster_templates/tables.py
sahara_dashboard/content/data_processing/clusters/cluster_templates/tabs.py
sahara_dashboard/content/data_processing/clusters/cluster_templates/tests.py
sahara_dashboard/content/data_processing/clusters/cluster_templates/views.py
sahara_dashboard/content/data_processing/clusters/cluster_templates/forms/__init__.py
sahara_dashboard/content/data_processing/clusters/cluster_templates/forms/import_forms.py
sahara_dashboard/content/data_processing/clusters/cluster_templates/workflows/__init__.py
sahara_dashboard/content/data_processing/clusters/cluster_templates/workflows/copy.py
sahara_dashboard/content/data_processing/clusters/cluster_templates/workflows/create.py
sahara_dashboard/content/data_processing/clusters/cluster_templates/workflows/edit.py
sahara_dashboard/content/data_processing/clusters/clusters/__init__.py
sahara_dashboard/content/data_processing/clusters/clusters/tables.py
sahara_dashboard/content/data_processing/clusters/clusters/tabs.py
sahara_dashboard/content/data_processing/clusters/clusters/tests.py
sahara_dashboard/content/data_processing/clusters/clusters/views.py
sahara_dashboard-19.0.0.dist-info/AUTHORS
sahara_dashboard-19.0.0.dist-info/LICENSE
sahara_dashboard-19.0.0.dist-info/METADATA
sahara_dashboard-19.0.0.dist-info/WHEEL
sahara_dashboard-19.0.0.dist-info/pbr.json
sahara_dashboard-19.0.0.dist-info/top_level.txt
sahara_dashboard-19.0.0.dist-info/RECORD
