Metadata-Version: 2.1
Name: sahara-dashboard
Version: 19.0.0
Summary: Sahara Management Dashboard
Home-page: https://docs.openstack.org/sahara/latest/
Author: OpenStack
Author-email: openstack-discuss@lists.openstack.org
License: UNKNOWN
Platform: UNKNOWN
Classifier: Environment :: OpenStack
Classifier: Intended Audience :: Information Technology
Classifier: Intended Audience :: System Administrators
Classifier: License :: OSI Approved :: Apache Software License
Classifier: Operating System :: POSIX :: Linux
Classifier: Programming Language :: Python
Classifier: Programming Language :: Python :: Implementation :: CPython
Classifier: Programming Language :: Python :: 3 :: Only
Classifier: Programming Language :: Python :: 3
Classifier: Programming Language :: Python :: 3.8
Classifier: Programming Language :: Python :: 3.9
Requires-Python: >=3.8
Requires-Dist: horizon (>=17.1.0)
Requires-Dist: keystoneauth1 (>=3.8.0)
Requires-Dist: oslo.log (>=3.36.0)
Requires-Dist: oslo.serialization (!=2.19.1,>=2.18.0)
Requires-Dist: pbr (!=2.1.0,>=2.0.0)
Requires-Dist: python-designateclient (>=2.7.0)
Requires-Dist: python-keystoneclient (>=3.22.0)
Requires-Dist: python-manilaclient (>=1.16.0)
Requires-Dist: python-neutronclient (>=6.7.0)
Requires-Dist: python-novaclient (>=9.1.0)
Requires-Dist: python-saharaclient (>=2.2.0)
Requires-Dist: pytz (>=2013.6)
